rpgrand/__init__.py
rpgrand/categories.py
rpgrand/cli.py
rpgrand/config_map.py
rpgrand/loaders.py
rpgrand/main.py
rpgrand/output.py
rpgrand/properties.py
rpgrand/rand.py
rpgrand/server.py
rpgrand-0.2.1.dist-info/METADATA
rpgrand-0.2.1.dist-info/RECORD
rpgrand-0.2.1.dist-info/WHEEL
rpgrand-0.2.1.dist-info/entry_points.txt
rpgrand-0.2.1.dist-info/top_level.txt
